telecomlib/__init__.py
telecomlib/getip/__init__.py
telecomlib/getip/getip.py
telecomlib/shell/__init__.py
telecomlib/shell/usage.py
telecomlib/star/__init__.py
telelib/__init__.py
telelib/ip_tools/__init__.py
telelib/ip_tools/getip.py
telelib/shell/__init__.py
telelib/shell/usage.py
telelib/star/__init__.py
torchversion/__init__.py
torchversion/shell/__init__.py
torchversion/shell/usage.py
torchversion/utils/__init__.py
torchversion/utils/torchsumary.py
torchversion/utils/version_pytorch.py
torchversion-0.0.4.dist-info/LICENSE
torchversion-0.0.4.dist-info/METADATA
torchversion-0.0.4.dist-info/WHEEL
torchversion-0.0.4.dist-info/entry_points.txt
torchversion-0.0.4.dist-info/top_level.txt
torchversion-0.0.4.dist-info/zip-safe
torchversion-0.0.4.dist-info/RECORD
